{
  "cli": {
    "version": ">= 16.17.4",
    "appVersionSource": "remote"
  },
  "build": {
    "development": {
      "developmentClient": true,
      "distribution": "internal"
    },
    "preview": {
      "distribution": "internal"
    },
    "production": {
      "autoIncrement": true
    },
    "apk": {
      "android": {
        "buildType": "apk"
      }
    },
    "apk-preview": {
      "android": {
        "buildType": "apk",
        "gradleCommand": ":app:assembleRelease"
      }
    }
  },
  "submit": {
    "production": {}
  }
}
